setup.py
mapq/__init__.py
mapq/core.py
mapq/geo.py
mapq.egg-info/PKG-INFO
mapq.egg-info/SOURCES.txt
mapq.egg-info/dependency_links.txt
mapq.egg-info/requires.txt
mapq.egg-info/top_level.txt